fattails/__init__.py
fattails/express.py
fattails/metrics.py
tests/__init__.py
tests/test_express.py
tests/test_metrics.py
fattails-0.0.4.dist-info/LICENSE
fattails-0.0.4.dist-info/METADATA
fattails-0.0.4.dist-info/WHEEL
fattails-0.0.4.dist-info/top_level.txt
fattails-0.0.4.dist-info/RECORD
