Metadata-Version: 2.1
Name: fattails
Version: 0.0.4
Summary: A package for fat-tailed statistics
Home-page: https://github.com/FergM/fattails/
Author: FergM
License: UNKNOWN
Platform: UNKNOWN
Classifier: Programming Language :: Python :: 3
Classifier: License :: OSI Approved :: MIT License
Classifier: Operating System :: OS Independent
Requires-Python: >=3.7
Requires-Dist: pandas (>=1.2.0)
Requires-Dist: matplotlib (>=3.3.3)
